<?xml version="1.0" encoding="utf-8"?>
<data pattern_url="">
  <item type="shape" opacity="1" index="0" shape_type="Rectangle" color="8459777 " xpos="204" ypos="300.3" width="726.7" height="48" rotation="0"/>
  <item type="image" opacity="1" index="1" source="assets/graphics/Lower Thirds/Design 18.png" xpos="152" ypos="283" width="512" height="49" rotation="0"/>
  <item type="text" opacity="1" index="2" font="Archivo Black" size="68" color="16777215@@@16777215@@@16777215@@@16777215@@@16777215@@@16777215@@@16777215@@@16777215@@@16777215@@@16777215@@@16777215@@@16777215@@@16777215@@@16777215@@@16777215@@@16777215@@@16777215@@@16777215@@@16777215@@@16777215@@@16777215@@@16777215@@@16777215@@@16777215@@@16777215" xpos="188.8" ypos="290.65" alignment="left" rotation="0" scalex="0.300445556640625" scaley="0.300445556640625" filter="true"><![CDATA[PRESENT YOUR VISUALS WELL]]></item>
  <item type="image" opacity="1" index="3" source="assets/graphics/Other Icons/51.png" xpos="563.8" ypos="278" width="64.5" height="70.1" rotation="0.7540698900022955"/>
  <item type="text" opacity="1" index="4" font="Arial" size="68" color="16777215@@@16777215@@@16777215@@@16777215@@@16777215@@@16777215@@@16777215@@@16777215@@@16777215@@@16777215@@@16777215@@@16777215@@@16777215@@@16777215@@@16777215@@@16777215@@@16777215@@@16777215@@@16777215@@@16777215@@@16777215@@@16777215@@@16777215@@@16777215@@@16777215@@@16777215@@@16777215@@@16777215@@@16777215@@@16777215@@@16777215@@@16777215@@@16777215" xpos="218.3" ypos="330.65" alignment="left" rotation="0" scalex="0.19293999671936035" scaley="0.19293999671936035" filter="true"><![CDATA[GREAT PRESENTATION FOR YOU AND ME]]></item>
  <item type="text" opacity="1" index="5" font="Arial" size="68" color="0@@@0@@@0@@@0@@@0@@@0@@@0@@@0@@@0" xpos="576" ypos="298" alignment="center" rotation="0" scalex="0.19293212890625" scaley="0.19293212890625" filter="true"><![CDATA[LOGO
HERE]]></item>
</data>